fdown_api/__init__.py
fdown_api/__main__.py
fdown_api/console.py
fdown_api/main.py
fdown_api-0.0.4.dist-info/licenses/LICENSE
fdown_api-0.0.4.dist-info/METADATA
fdown_api-0.0.4.dist-info/WHEEL
fdown_api-0.0.4.dist-info/entry_points.txt
fdown_api-0.0.4.dist-info/top_level.txt
fdown_api-0.0.4.dist-info/RECORD
