Metadata-Version: 2.4
Name: fdown-api
Version: 0.0.4
Summary: Unofficial Python wrapper for fdown.net
Home-page: https://github.com/Simatwa/fdown-api
Author: Smartwa
Author-email: simatwacaleb@proton.me
Maintainer: Smartwa
License: GPLv3
Project-URL: Bug Report, https://github.com/Simatwa/fdown-api/issues/new
Project-URL: Homepage, https://github.com/Simatwa/fdown-api
Project-URL: Source Code, https://github.com/Simatwa/fdown-api
Project-URL: Issue Tracker, https://github.com/Simatwa/fdown-api/issues
Project-URL: Download, https://github.com/Simatwa/fdown-api/releases
Project-URL: Documentation, https://github.com/Simatwa/fdown-api/
Keywords: facebook,fdown
Classifier: License :: OSI Approved :: MIT License
Classifier: Intended Audience :: Developers
Classifier: Intended Audience :: Developers
Classifier: Natural Language :: English
Classifier: License :: Free For Home Use
Classifier: Intended Audience :: Customer Service
Classifier: Programming Language :: Python
Classifier: Topic :: Software Development :: Libraries :: Python Modules
Classifier: Programming Language :: Python :: 3 :: Only
Classifier: Programming Language :: Python :: 3.10
Classifier: Programming Language :: Python :: 3.11
Classifier: Programming Language :: Python :: 3.12
Classifier: Programming Language :: Python :: 3.13
Requires-Python: >=3.10
License-File: LICENSE
Requires-Dist: cloudscraper>=1.2.71
Requires-Dist: bs4>=0.0.1
Provides-Extra: cli
Requires-Dist: tqdm>=4.66.3; extra == "cli"
Requires-Dist: colorama>=0.4.6; extra == "cli"
Dynamic: author
Dynamic: author-email
Dynamic: classifier
Dynamic: description
Dynamic: description-content-type
Dynamic: home-page
Dynamic: keywords
Dynamic: license
Dynamic: license-file
Dynamic: maintainer
Dynamic: project-url
Dynamic: provides-extra
Dynamic: requires-dist
Dynamic: requires-python
Dynamic: summary
